toolfuse/__init__.py
toolfuse/base.py
toolfuse/models.py
toolfuse/multi.py
toolfuse/util.py
toolfuse-0.1.25.dist-info/LICENSE
toolfuse-0.1.25.dist-info/METADATA
toolfuse-0.1.25.dist-info/WHEEL
toolfuse-0.1.25.dist-info/entry_points.txt
toolfuse-0.1.25.dist-info/RECORD
