Metadata-Version: 2.1
Name: toolfuse
Version: 0.1.25
Summary: Tools for AI agents
License: MIT
Author: Patrick Barker
Author-email: patrickbarkerco@gmail.com
Requires-Python: >=3.10,<4.0
Classifier: License :: OSI Approved :: MIT License
Classifier: Programming Language :: Python :: 3
Classifier: Programming Language :: Python :: 3.10
Classifier: Programming Language :: Python :: 3.11
Requires-Dist: docstring-parser (>=0.15,<0.16)
Requires-Dist: jsonschema (>=4.22.0,<5.0.0)
Requires-Dist: openai (>=1.12.0,<2.0.0)
Requires-Dist: python-dotenv (>=1.0.1,<2.0.0)
Requires-Dist: toolcore (>=0.1.0,<0.2.0)
Requires-Dist: urllib3 (>=1.26.0,<2.0.0)
